{
    "error": false,
    "filename": "ProjectElixir_3.3_alioth-13.0-20221123-0537-OFFICIAL.zip",
    "datetime": 1669181804,
    "size": 1867431134,
    "url": "https://private.projectelixiros.com/thirteen/alioth/ProjectElixir_3.3_alioth-13.0-20221123-0537-OFFICIAL.zip",
    "filehash": "b236159e5553742c861d62332b157374",
    "version": "13.0",
    "id": "3e5110594adf73e0b1a2235dff34960c70537969af38ae9745f17ae664763081",       
    "tg_username": "theangelofdead01",
    "device_name": "Redmi K40/POCO F3/Mi 11x",
    "device": "alioth",
    "xda_thread": "https://forum.xda-developers.com/t/android-13-alioth-project-elixir-for-poco-f3-official.4488415/",
    "is_active": true     
}
