{
    "error": false,
    "filename": "ProjectElixir_2.1_fajita-12.1-20220908-0835-OFFICIAL.zip",
    "datetime": 1662625936,
    "size": 1450213479,
    "url": "https://private.projectelixiros.com/twelve/fajita/ProjectElixir_2.1_fajita-12.1-20220908-0835-OFFICIAL.zip",
    "filehash": "b1255c0ace3da9e8227616f1aad6b1e8",
    "version": "12.1",
    "id": "3a18f7b4ac6af528153d73d797052a79766f0970f1512f75c51a0f07796e923d",
    "tg_username": "CR7Raees",
    "device_name": "Oneplus 6T",
    "device": "fajita",
    "xda_thread": "https://forum.xda-developers.com/t/rom-12-1-fajita-project-elixir-official-oneplus-6t-aosp.4472911/",
    "is_active": true
}
