{
    "error": false,
    "filename": "ProjectElixir_3.5_ginkgo-13.0-20230111-1845-OFFICIAL.zip",
    "datetime": 1673462700,
    "size": 1889872965,
    "url": "https://private.projectelixiros.com/thirteen/ginkgo/ProjectElixir_3.5_ginkgo-13.0-20230111-1845-OFFICIAL.zip",
    "filehash": "3a5e80fb0cfb8dc542fc9272b17f1489",
    "version": "13.0",
    "id": "856749c0870ad39390d841e64bfb03ff55a92b6308b9ecc9fa268e3bbdedacee",       
    "tg_username": "WeeboDemon",
    "device_name": "Redmi Note 8/8T",
    "device": "ginkgo",
    "xda_thread": "https://forum.xda-developers.com/t/rom-13-0-official-unified-project-elixir-3-x-for-redmi-note-8-8t.4506301",
    "is_active": true     
}
