{
    "error": false,
    "filename": "ProjectElixir_3.11_guacamole-13.0-20230819-1126-OFFICIAL.zip",
    "datetime": 1692437160,
    "size": 1938500796,
    "url": "https://private.projectelixiros.com/thirteen/guacamole/ProjectElixir_3.11_guacamole-13.0-20230819-1126-OFFICIAL.zip",
    "filehash": "d3c878a97a97250decf01d1f7e849eee",
    "version": "13.0",
    "id": "7babe2951c3d0b3062d21550d589dc1c771ca816e8a48bdb291428aa11b4875c",       
    "tg_username": "mhmdeveloper",
    "device_name": "OnePlus 7 Pro",
    "device": "guacamole",
    "xda_thread": "https://forum.xda-developers.com/t/rom-13-0-guacamole-oos-cam-project-elixir-official-oneplus-7-pro-aosp.4496677/",
    "is_active": true     
}
