{
    "error": false,
    "filename": "ProjectElixir_3.0_RMX2170-13.0-20220830-1637-BETA-OFFICIAL.zip",
    "datetime": 1661877277,
    "size": 1986048095,
    "url": "https://private.projectelixiros.com/twelve/RMX2170/ProjectElixir_3.0_RMX2170-13.0-20220830-1637-BETA-OFFICIAL.zip",
    "filehash": "0767175a0854aeebb8bc57293ef29a64",
    "version": "13.0",
    "id": "2d63d9764f77cb0bb6dbf56065c909f8c616b06feddfdd9cda11818988dfa667",
    "tg_username": "marshmello_61",
    "device_name": "Realme 7 Pro",
    "device": "RMX2170",
    "xda_thread": "https://forum.xda-developers.com/t/android-13-rmx2170-project-elixir-for-realme-7-pro-official.4487083/",
    "is_active": true
}
