{
    "error": false,
    "filename": "ProjectElixir_3.8_toco-13.0-20230522-0548-OFFICIAL.zip",
    "datetime": 1684727280,
    "size": 2166747575,
    "url": "https://private.projectelixiros.com/thirteen/toco/ProjectElixir_3.8_toco-13.0-20230522-0548-OFFICIAL.zip",
    "filehash": "5f110c78f1c3fa680b9c73f768c7f3af",
    "version": "13.0",
    "id": "e30f4e035a75f0cd2b63a5250f66e08aea18256c64a3bd270ccb95fc764997e1",       
    "tg_username": "DennisMurimiWachira",
    "device_name": "Xiaomi Mi Note 10 Lite",
    "device": "toco",
    "xda_thread": "https://forum.xda-developers.com/t/rom-13-0-toco-official-project-elixir-3-x.4498763/",
    "is_active": true     
}
