{
    "error": false,
    "filename": "ProjectElixir_3.8_vayu-13.0-20230523-0925-OFFICIAL.zip",
    "datetime": 1684826700,
    "size": 2059870907,
    "url": "https://private.projectelixiros.com/thirteen/vayu/ProjectElixir_3.8_vayu-13.0-20230523-0925-OFFICIAL.zip",
    "filehash": "3acc47e6e22d7ca991578240ec5873cc",
    "version": "13.0",
    "id": "fe1b9c2c6904dc4e21f8897edd5376a76c380a2e3f59ef5636400e4c04ca579f",       
    "tg_username": "chandlerbigg",
    "device_name": "Poco X3 Pro",
    "device": "vayu",
    "xda_thread": "https://forum.xda-developers.com/t/4489435/",
    "is_active": true     
}
