{
    "error": false,
    "filename": "ProjectElixir_4.0_X00TD-14.0-20240106-1600-OFFICIAL.zip",
    "datetime": 1704556800,
    "size": 2028444135,
    "url": "https://private.projectelixiros.com/fourteen/X00TD/ProjectElixir_4.0_X00TD-14.0-20240106-1600-OFFICIAL.zip",
    "filehash": "df50964d05e74c4a63e234e6d5ba7c99",
    "version": "14.0",
    "id": "579ebc2cb9df8301347b3c5741aa3dac63d3dcab20d81f559fc3ee36e404eb12",
    "tg_username": "NotHarshhaa",
    "device_name": "Asus Zenfone Max Pro M1",
    "device": "X00TD",
    "xda_thread": "https://xdaforums.com/t/x00td-rom-project-elixir-v4-0-android-14-0-aosp-official-06-01-2024.4649511/",
    "is_active": true
}
